findpg
