Metadata-Version: 1.1
Name: findpg
Version: 2.3
Summary: Find the best suited version of PostgreSQL to restore a dump
Home-page: https://github.com/cecton/findpg
Author: Cecile Tonglet
Author-email: cecile.tonglet@gmail.com
License: MIT
Keywords: postgres database dump restore
Platform: UNKNOWN
Classifier: Development Status :: 4 - Beta
Classifier: Topic :: Database
Classifier: License :: OSI Approved :: MIT License
